partehmath/__init__.py
partehmath/math.py
partehmath-1.1.0.dist-info/LICENSE
partehmath-1.1.0.dist-info/METADATA
partehmath-1.1.0.dist-info/WHEEL
partehmath-1.1.0.dist-info/top_level.txt
partehmath-1.1.0.dist-info/RECORD
