Metadata-Version: 2.1
Name: partehmath
Version: 1.1.0
Summary: A bad numpy clone with less features
Author-email: PartehDev <parteh0754@vivaldi.net>
License: Copyright 2022 PartehDev
Project-URL: Homepage, https://github.com/PartehDev/PartehMath
Project-URL: Bug Tracker, https://github.com/PartehDev/PartehMath/issues
Classifier: Programming Language :: Python :: 3
Classifier: License :: OSI Approved :: MIT License
Classifier: Operating System :: OS Independent
Requires-Python: >=3.7
License-File: LICENSE
